{
  "url": "https://qa-reports.linaro.org/api/testruns/1056403/",
  "id": 1056403,
  "tests_file": "https://qa-reports.linaro.org/api/testruns/1056403/tests_file/",
  "metrics_file": "https://qa-reports.linaro.org/api/testruns/1056403/metrics_file/",
  "metadata_file": "https://qa-reports.linaro.org/api/testruns/1056403/metadata_file/",
  "log_file": "https://qa-reports.linaro.org/api/testruns/1056403/log_file/",
  "tests": "https://qa-reports.linaro.org/api/testruns/1056403/tests/",
  "metrics": "https://qa-reports.linaro.org/api/testruns/1056403/metrics/",
  "created_at": "2018-11-15T12:04:51.785171Z",
  "completed": true,
  "datetime": "2018-11-15T12:04:51.784936Z",
  "build_url": null,
  "job_id": "509271",
  "job_status": "Complete",
  "job_url": "https://lkft.validation.linaro.org/scheduler/job/509271",
  "resubmit_url": null,
  "data_processed": true,
  "status_recorded": true,
  "build": "https://qa-reports.linaro.org/api/builds/11110/",
  "environment": "https://qa-reports.linaro.org/api/environments/430/"
}