{
  "url": "https://qa-reports.linaro.org/api/testruns/144454/",
  "id": 144454,
  "tests_file": "https://qa-reports.linaro.org/api/testruns/144454/tests_file/",
  "metrics_file": "https://qa-reports.linaro.org/api/testruns/144454/metrics_file/",
  "metadata_file": "https://qa-reports.linaro.org/api/testruns/144454/metadata_file/",
  "log_file": "https://qa-reports.linaro.org/api/testruns/144454/log_file/",
  "tests": "https://qa-reports.linaro.org/api/testruns/144454/tests/",
  "metrics": "https://qa-reports.linaro.org/api/testruns/144454/metrics/",
  "created_at": "2017-11-18T14:31:41.705054Z",
  "completed": true,
  "datetime": "2017-11-18T14:31:41.704862Z",
  "build_url": null,
  "job_id": "61319",
  "job_status": "Complete",
  "job_url": "https://lkft.validation.linaro.org/scheduler/job/61319",
  "resubmit_url": null,
  "data_processed": true,
  "status_recorded": true,
  "build": "https://qa-reports.linaro.org/api/builds/3083/",
  "environment": "https://qa-reports.linaro.org/api/environments/70/"
}