{
  "url": "https://qa-reports.linaro.org/api/testruns/186043/",
  "id": 186043,
  "tests_file": "https://qa-reports.linaro.org/api/testruns/186043/tests_file/",
  "metrics_file": "https://qa-reports.linaro.org/api/testruns/186043/metrics_file/",
  "metadata_file": "https://qa-reports.linaro.org/api/testruns/186043/metadata_file/",
  "log_file": "https://qa-reports.linaro.org/api/testruns/186043/log_file/",
  "tests": "https://qa-reports.linaro.org/api/testruns/186043/tests/",
  "metrics": "https://qa-reports.linaro.org/api/testruns/186043/metrics/",
  "created_at": "2018-01-18T17:17:05.757409Z",
  "completed": true,
  "datetime": "2018-01-18T17:17:05.757226Z",
  "build_url": null,
  "job_id": "98217",
  "job_status": "Complete",
  "job_url": "https://lkft.validation.linaro.org/scheduler/job/98217",
  "resubmit_url": null,
  "data_processed": true,
  "status_recorded": true,
  "build": "https://qa-reports.linaro.org/api/builds/3889/",
  "environment": "https://qa-reports.linaro.org/api/environments/19/"
}