{
  "url": "https://qa-reports.linaro.org/api/testruns/188236/",
  "id": 188236,
  "tests_file": "https://qa-reports.linaro.org/api/testruns/188236/tests_file/",
  "metrics_file": "https://qa-reports.linaro.org/api/testruns/188236/metrics_file/",
  "metadata_file": "https://qa-reports.linaro.org/api/testruns/188236/metadata_file/",
  "log_file": "https://qa-reports.linaro.org/api/testruns/188236/log_file/",
  "tests": "https://qa-reports.linaro.org/api/testruns/188236/tests/",
  "metrics": "https://qa-reports.linaro.org/api/testruns/188236/metrics/",
  "created_at": "2018-01-22T11:18:26.985849Z",
  "completed": true,
  "datetime": "2018-01-22T11:18:26.985648Z",
  "build_url": null,
  "job_id": "100566",
  "job_status": "Complete",
  "job_url": "https://lkft.validation.linaro.org/scheduler/job/100566",
  "resubmit_url": null,
  "data_processed": true,
  "status_recorded": true,
  "build": "https://qa-reports.linaro.org/api/builds/3989/",
  "environment": "https://qa-reports.linaro.org/api/environments/57/"
}