{
  "url": "https://qa-reports.linaro.org/api/testruns/520510/",
  "id": 520510,
  "tests_file": "https://qa-reports.linaro.org/api/testruns/520510/tests_file/",
  "metrics_file": "https://qa-reports.linaro.org/api/testruns/520510/metrics_file/",
  "metadata_file": "https://qa-reports.linaro.org/api/testruns/520510/metadata_file/",
  "log_file": "https://qa-reports.linaro.org/api/testruns/520510/log_file/",
  "tests": "https://qa-reports.linaro.org/api/testruns/520510/tests/",
  "metrics": "https://qa-reports.linaro.org/api/testruns/520510/metrics/",
  "created_at": "2018-06-05T21:59:12.673537Z",
  "completed": true,
  "datetime": "2018-06-05T21:59:12.673316Z",
  "build_url": null,
  "job_id": "253550",
  "job_status": "Incomplete",
  "job_url": "https://lkft.validation.linaro.org/scheduler/job/253550",
  "resubmit_url": null,
  "data_processed": true,
  "status_recorded": true,
  "build": "https://qa-reports.linaro.org/api/builds/7109/",
  "environment": "https://qa-reports.linaro.org/api/environments/302/"
}