{
  "url": "https://qa-reports.linaro.org/api/testruns/582459/",
  "id": 582459,
  "tests_file": "https://qa-reports.linaro.org/api/testruns/582459/tests_file/",
  "metrics_file": "https://qa-reports.linaro.org/api/testruns/582459/metrics_file/",
  "metadata_file": "https://qa-reports.linaro.org/api/testruns/582459/metadata_file/",
  "log_file": "https://qa-reports.linaro.org/api/testruns/582459/log_file/",
  "tests": "https://qa-reports.linaro.org/api/testruns/582459/tests/",
  "metrics": "https://qa-reports.linaro.org/api/testruns/582459/metrics/",
  "created_at": "2018-06-12T17:49:32.621296Z",
  "completed": true,
  "datetime": "2018-06-12T17:49:32.621082Z",
  "build_url": null,
  "job_id": "273184",
  "job_status": "Complete",
  "job_url": "https://lkft.validation.linaro.org/scheduler/job/273184",
  "resubmit_url": null,
  "data_processed": true,
  "status_recorded": true,
  "build": "https://qa-reports.linaro.org/api/builds/7452/",
  "environment": "https://qa-reports.linaro.org/api/environments/70/"
}