{
  "url": "https://qa-reports.linaro.org/api/testruns/609685/",
  "id": 609685,
  "tests_file": "https://qa-reports.linaro.org/api/testruns/609685/tests_file/",
  "metrics_file": "https://qa-reports.linaro.org/api/testruns/609685/metrics_file/",
  "metadata_file": "https://qa-reports.linaro.org/api/testruns/609685/metadata_file/",
  "log_file": "https://qa-reports.linaro.org/api/testruns/609685/log_file/",
  "tests": "https://qa-reports.linaro.org/api/testruns/609685/tests/",
  "metrics": "https://qa-reports.linaro.org/api/testruns/609685/metrics/",
  "created_at": "2018-06-17T10:22:05.544175Z",
  "completed": false,
  "datetime": "2018-06-17T10:22:05.543975Z",
  "build_url": null,
  "job_id": "285601",
  "job_status": "Incomplete",
  "job_url": "https://lkft.validation.linaro.org/scheduler/job/285601",
  "resubmit_url": null,
  "data_processed": true,
  "status_recorded": true,
  "build": "https://qa-reports.linaro.org/api/builds/7612/",
  "environment": "https://qa-reports.linaro.org/api/environments/65/"
}