{
  "url": "https://qa-reports.linaro.org/api/testruns/793706/",
  "id": 793706,
  "tests_file": "https://qa-reports.linaro.org/api/testruns/793706/tests_file/",
  "metrics_file": "https://qa-reports.linaro.org/api/testruns/793706/metrics_file/",
  "metadata_file": "https://qa-reports.linaro.org/api/testruns/793706/metadata_file/",
  "log_file": "https://qa-reports.linaro.org/api/testruns/793706/log_file/",
  "tests": "https://qa-reports.linaro.org/api/testruns/793706/tests/",
  "metrics": "https://qa-reports.linaro.org/api/testruns/793706/metrics/",
  "created_at": "2018-07-28T08:44:01.867182Z",
  "completed": true,
  "datetime": "2018-07-28T08:44:01.866957Z",
  "build_url": null,
  "job_id": "345770",
  "job_status": "Complete",
  "job_url": "https://lkft.validation.linaro.org/scheduler/job/345770",
  "resubmit_url": null,
  "data_processed": true,
  "status_recorded": true,
  "build": "https://qa-reports.linaro.org/api/builds/8361/",
  "environment": "https://qa-reports.linaro.org/api/environments/302/"
}