{
  "url": "https://qa-reports.linaro.org/api/testruns/809106/",
  "id": 809106,
  "tests_file": "https://qa-reports.linaro.org/api/testruns/809106/tests_file/",
  "metrics_file": "https://qa-reports.linaro.org/api/testruns/809106/metrics_file/",
  "metadata_file": "https://qa-reports.linaro.org/api/testruns/809106/metadata_file/",
  "log_file": "https://qa-reports.linaro.org/api/testruns/809106/log_file/",
  "tests": "https://qa-reports.linaro.org/api/testruns/809106/tests/",
  "metrics": "https://qa-reports.linaro.org/api/testruns/809106/metrics/",
  "created_at": "2018-08-02T11:57:10.630733Z",
  "completed": true,
  "datetime": "2018-08-02T11:57:10.630511Z",
  "build_url": null,
  "job_id": "351439",
  "job_status": "Complete",
  "job_url": "https://lkft.validation.linaro.org/scheduler/job/351439",
  "resubmit_url": null,
  "data_processed": true,
  "status_recorded": true,
  "build": "https://qa-reports.linaro.org/api/builds/8460/",
  "environment": "https://qa-reports.linaro.org/api/environments/66/"
}