{
  "url": "https://qa-reports.linaro.org/api/testruns/817543/",
  "id": 817543,
  "tests_file": "https://qa-reports.linaro.org/api/testruns/817543/tests_file/",
  "metrics_file": "https://qa-reports.linaro.org/api/testruns/817543/metrics_file/",
  "metadata_file": "https://qa-reports.linaro.org/api/testruns/817543/metadata_file/",
  "log_file": "https://qa-reports.linaro.org/api/testruns/817543/log_file/",
  "tests": "https://qa-reports.linaro.org/api/testruns/817543/tests/",
  "metrics": "https://qa-reports.linaro.org/api/testruns/817543/metrics/",
  "created_at": "2018-08-04T15:07:03.686977Z",
  "completed": true,
  "datetime": "2018-08-04T15:07:03.686759Z",
  "build_url": null,
  "job_id": "356122",
  "job_status": "Complete",
  "job_url": "https://lkft.validation.linaro.org/scheduler/job/356122",
  "resubmit_url": null,
  "data_processed": true,
  "status_recorded": true,
  "build": "https://qa-reports.linaro.org/api/builds/8527/",
  "environment": "https://qa-reports.linaro.org/api/environments/57/"
}