{
  "url": "https://qa-reports.linaro.org/api/testruns/844605/",
  "id": 844605,
  "tests_file": "https://qa-reports.linaro.org/api/testruns/844605/tests_file/",
  "metrics_file": "https://qa-reports.linaro.org/api/testruns/844605/metrics_file/",
  "metadata_file": "https://qa-reports.linaro.org/api/testruns/844605/metadata_file/",
  "log_file": "https://qa-reports.linaro.org/api/testruns/844605/log_file/",
  "tests": "https://qa-reports.linaro.org/api/testruns/844605/tests/",
  "metrics": "https://qa-reports.linaro.org/api/testruns/844605/metrics/",
  "created_at": "2018-08-16T05:05:50.448152Z",
  "completed": true,
  "datetime": "2018-08-16T05:05:50.447931Z",
  "build_url": null,
  "job_id": "370881",
  "job_status": "Complete",
  "job_url": "https://lkft.validation.linaro.org/scheduler/job/370881",
  "resubmit_url": null,
  "data_processed": true,
  "status_recorded": true,
  "build": "https://qa-reports.linaro.org/api/builds/8763/",
  "environment": "https://qa-reports.linaro.org/api/environments/66/"
}