{
  "url": "https://qa-reports.linaro.org/api/testjobs/1053902/",
  "external_url": "https://lkft.validation.linaro.org/scheduler/job/381005",
  "definition": "https://qa-reports.linaro.org/api/testjobs/1053902/definition/",
  "name": "lkft-ltp-timers-linux-4.9.y-355",
  "environment": "x86",
  "created_at": "2018-08-21T09:15:55.623580Z",
  "submitted_at": "2018-08-21T09:15:56.190808Z",
  "fetched_at": "2018-08-21T17:04:43.499233Z",
  "submitted": true,
  "fetched": true,
  "fetch_attempts": 0,
  "last_fetch_attempt": "2018-08-21T17:04:41.421831Z",
  "failure": null,
  "can_resubmit": false,
  "resubmitted_count": 0,
  "job_id": "381005",
  "job_status": "Complete",
  "backend": "https://qa-reports.linaro.org/api/backends/2/",
  "testrun": "https://qa-reports.linaro.org/api/testruns/862112/",
  "target": "https://qa-reports.linaro.org/api/projects/23/",
  "target_build": "https://qa-reports.linaro.org/api/builds/8882/",
  "parent_job": null
}