{
  "url": "https://qa-reports.linaro.org/api/testjobs/1079856/",
  "external_url": "https://lkft.validation.linaro.org/scheduler/job/395985",
  "definition": "https://qa-reports.linaro.org/api/testjobs/1079856/definition/",
  "name": "lkft-ltp-timers-linux-4.9.y-365",
  "environment": "x15",
  "created_at": "2018-08-28T06:32:41.787453Z",
  "submitted_at": "2018-08-28T06:32:42.391253Z",
  "fetched_at": "2018-08-28T07:45:10.904283Z",
  "submitted": true,
  "fetched": true,
  "fetch_attempts": 0,
  "last_fetch_attempt": "2018-08-28T07:45:08.871543Z",
  "failure": null,
  "can_resubmit": false,
  "resubmitted_count": 0,
  "job_id": "395985",
  "job_status": "Complete",
  "backend": "https://qa-reports.linaro.org/api/backends/2/",
  "testrun": "https://qa-reports.linaro.org/api/testruns/887036/",
  "target": "https://qa-reports.linaro.org/api/projects/23/",
  "target_build": "https://qa-reports.linaro.org/api/builds/9042/",
  "parent_job": null
}