{
  "url": "https://qa-reports.linaro.org/api/testjobs/1093686/",
  "external_url": "https://lkft.validation.linaro.org/scheduler/job/404576",
  "definition": "https://qa-reports.linaro.org/api/testjobs/1093686/definition/",
  "name": "lkft-kselftests-linux-4.4.y-300",
  "environment": "juno-r2",
  "created_at": "2018-09-03T17:18:51.555229Z",
  "submitted_at": "2018-09-03T17:18:52.097823Z",
  "fetched_at": "2018-09-03T22:07:52.232975Z",
  "submitted": true,
  "fetched": true,
  "fetch_attempts": 0,
  "last_fetch_attempt": "2018-09-03T22:07:49.026115Z",
  "failure": "{'case': 'job', 'error_type': 'Infrastructure', 'result': 'fail', 'definition': 'lava', 'error_msg': 'lava_test_shell connection dropped.'}",
  "can_resubmit": true,
  "resubmitted_count": 0,
  "job_id": "404576",
  "job_status": "Incomplete",
  "backend": "https://qa-reports.linaro.org/api/backends/2/",
  "testrun": "https://qa-reports.linaro.org/api/testruns/902753/",
  "target": "https://qa-reports.linaro.org/api/projects/40/",
  "target_build": "https://qa-reports.linaro.org/api/builds/9258/",
  "parent_job": null
}