{
  "url": "https://qa-reports.linaro.org/api/testjobs/1110635/",
  "external_url": "https://lkft.validation.linaro.org/scheduler/job/413219",
  "definition": "https://qa-reports.linaro.org/api/testjobs/1110635/definition/",
  "name": "lkft-ltp-filecaps-linux-4.9.y-374",
  "environment": "qemu_i386",
  "created_at": "2018-09-11T15:53:35.389373Z",
  "submitted_at": "2018-09-11T15:53:35.967653Z",
  "fetched_at": "2018-09-11T16:41:49.240791Z",
  "submitted": true,
  "fetched": true,
  "fetch_attempts": 0,
  "last_fetch_attempt": "2018-09-11T16:41:47.538753Z",
  "failure": null,
  "can_resubmit": false,
  "resubmitted_count": 0,
  "job_id": "413219",
  "job_status": "Complete",
  "backend": "https://qa-reports.linaro.org/api/backends/2/",
  "testrun": "https://qa-reports.linaro.org/api/testruns/915672/",
  "target": "https://qa-reports.linaro.org/api/projects/23/",
  "target_build": "https://qa-reports.linaro.org/api/builds/9499/",
  "parent_job": null
}