{
  "url": "https://qa-reports.linaro.org/api/testjobs/1156238/",
  "external_url": "https://lkft.validation.linaro.org/scheduler/job/457355",
  "definition": "https://qa-reports.linaro.org/api/testjobs/1156238/definition/",
  "name": "lkft-ltp-cap_bounds-linux-4.4.y-329",
  "environment": "x15",
  "created_at": "2018-10-09T14:49:28.785433Z",
  "submitted_at": "2018-10-09T14:49:29.457612Z",
  "fetched_at": "2018-10-09T15:22:40.245817Z",
  "submitted": true,
  "fetched": true,
  "fetch_attempts": 0,
  "last_fetch_attempt": "2018-10-09T15:22:38.429408Z",
  "failure": null,
  "can_resubmit": false,
  "resubmitted_count": 0,
  "job_id": "457355",
  "job_status": "Complete",
  "backend": "https://qa-reports.linaro.org/api/backends/2/",
  "testrun": "https://qa-reports.linaro.org/api/testruns/961564/",
  "target": "https://qa-reports.linaro.org/api/projects/40/",
  "target_build": "https://qa-reports.linaro.org/api/builds/10161/",
  "parent_job": null
}