{
  "url": "https://qa-reports.linaro.org/api/testjobs/1164459/",
  "external_url": "https://lkft.validation.linaro.org/scheduler/job/465217",
  "definition": "https://qa-reports.linaro.org/api/testjobs/1164459/definition/",
  "name": "lkft-ltp-fs_perms_simple-linux-4.9.y-401",
  "environment": "juno-r2",
  "created_at": "2018-10-12T15:52:40.882052Z",
  "submitted_at": "2018-10-12T15:52:41.466307Z",
  "fetched_at": "2018-10-12T18:27:26.879504Z",
  "submitted": true,
  "fetched": true,
  "fetch_attempts": 0,
  "last_fetch_attempt": "2018-10-12T18:27:25.063050Z",
  "failure": null,
  "can_resubmit": false,
  "resubmitted_count": 0,
  "job_id": "465217",
  "job_status": "Complete",
  "backend": "https://qa-reports.linaro.org/api/backends/2/",
  "testrun": "https://qa-reports.linaro.org/api/testruns/969693/",
  "target": "https://qa-reports.linaro.org/api/projects/23/",
  "target_build": "https://qa-reports.linaro.org/api/builds/10270/",
  "parent_job": null
}