{
  "url": "https://qa-reports.linaro.org/api/testjobs/1216515/",
  "external_url": "https://lkft.validation.linaro.org/scheduler/job/492174",
  "definition": "https://qa-reports.linaro.org/api/testjobs/1216515/definition/",
  "name": "lkft-ltp-securebits-linux-4.9.y-409",
  "environment": "i386",
  "created_at": "2018-11-02T14:33:03.440046Z",
  "submitted_at": "2018-11-02T14:33:03.988116Z",
  "fetched_at": "2018-11-02T20:00:23.470759Z",
  "submitted": true,
  "fetched": true,
  "fetch_attempts": 0,
  "last_fetch_attempt": "2018-11-02T20:00:21.878421Z",
  "failure": null,
  "can_resubmit": false,
  "resubmitted_count": 0,
  "job_id": "492174",
  "job_status": "Complete",
  "backend": "https://qa-reports.linaro.org/api/backends/2/",
  "testrun": "https://qa-reports.linaro.org/api/testruns/1022559/",
  "target": "https://qa-reports.linaro.org/api/projects/23/",
  "target_build": "https://qa-reports.linaro.org/api/builds/10786/",
  "parent_job": null
}