{
  "url": "https://qa-reports.linaro.org/api/testjobs/1240419/",
  "external_url": "https://lkft.validation.linaro.org/scheduler/job/503507",
  "definition": "https://qa-reports.linaro.org/api/testjobs/1240419/definition/",
  "name": "lkft-ltp-fs_perms_simple-linux-4.9.y-414",
  "environment": "qemu_arm64",
  "created_at": "2018-11-11T22:04:56.860029Z",
  "submitted_at": "2018-11-11T22:04:57.429547Z",
  "fetched_at": "2018-11-11T22:26:28.036981Z",
  "submitted": true,
  "fetched": true,
  "fetch_attempts": 0,
  "last_fetch_attempt": "2018-11-11T22:26:26.282800Z",
  "failure": null,
  "can_resubmit": false,
  "resubmitted_count": 0,
  "job_id": "503507",
  "job_status": "Complete",
  "backend": "https://qa-reports.linaro.org/api/backends/2/",
  "testrun": "https://qa-reports.linaro.org/api/testruns/1045452/",
  "target": "https://qa-reports.linaro.org/api/projects/23/",
  "target_build": "https://qa-reports.linaro.org/api/builds/11025/",
  "parent_job": null
}