{
  "url": "https://qa-reports.linaro.org/api/testjobs/1241377/",
  "external_url": "https://lkft.validation.linaro.org/scheduler/job/504475",
  "definition": "https://qa-reports.linaro.org/api/testjobs/1241377/definition/",
  "name": "lkft-kselftests-linux-4.9.y-415",
  "environment": "qemu_arm64",
  "created_at": "2018-11-11T23:49:37.557294Z",
  "submitted_at": "2018-11-11T23:49:38.150945Z",
  "fetched_at": "2018-11-12T03:07:53.688758Z",
  "submitted": true,
  "fetched": true,
  "fetch_attempts": 0,
  "last_fetch_attempt": "2018-11-12T03:07:48.008799Z",
  "failure": "{'case': 'job', 'error_msg': 'lava-test-shell timed out after 2473 seconds', 'definition': 'lava', 'error_type': 'Job', 'result': 'fail'}",
  "can_resubmit": true,
  "resubmitted_count": 0,
  "job_id": "504475",
  "job_status": "Incomplete",
  "backend": "https://qa-reports.linaro.org/api/backends/2/",
  "testrun": "https://qa-reports.linaro.org/api/testruns/1046538/",
  "target": "https://qa-reports.linaro.org/api/projects/23/",
  "target_build": "https://qa-reports.linaro.org/api/builds/11033/",
  "parent_job": null
}