{
  "url": "https://qa-reports.linaro.org/api/testjobs/1322050/",
  "external_url": "https://lkft.validation.linaro.org/scheduler/job/546596",
  "definition": "https://qa-reports.linaro.org/api/testjobs/1322050/definition/",
  "name": "lkft-kselftests-vsyscall-mode-native-linux-4.4.y-372",
  "environment": "x86",
  "created_at": "2018-12-13T23:52:11.137236Z",
  "submitted_at": "2018-12-13T23:52:11.965121Z",
  "fetched_at": "2018-12-14T00:50:48.970540Z",
  "submitted": true,
  "fetched": true,
  "fetch_attempts": 0,
  "last_fetch_attempt": "2018-12-14T00:50:42.624762Z",
  "failure": "{'definition': 'lava', 'error_msg': 'lava-test-shell timed out after 2422 seconds', 'case': 'job', 'error_type': 'Test', 'result': 'fail'}",
  "can_resubmit": false,
  "resubmitted_count": 0,
  "job_id": "546596",
  "job_status": "Incomplete",
  "backend": "https://qa-reports.linaro.org/api/backends/2/",
  "testrun": "https://qa-reports.linaro.org/api/testruns/1127592/",
  "target": "https://qa-reports.linaro.org/api/projects/40/",
  "target_build": "https://qa-reports.linaro.org/api/builds/11919/",
  "parent_job": null
}