{
  "url": "https://qa-reports.linaro.org/api/testjobs/154422/",
  "external_url": "https://lkft.validation.linaro.org/scheduler/job/70845",
  "definition": "https://qa-reports.linaro.org/api/testjobs/154422/definition/",
  "name": "lkft-libhugetlbfs-linux-4.4.y-63",
  "environment": "juno-r2",
  "created_at": "2017-12-04T17:12:24.440882Z",
  "submitted_at": "2017-12-04T17:12:24.932320Z",
  "fetched_at": "2017-12-04T21:39:14.511091Z",
  "submitted": true,
  "fetched": true,
  "fetch_attempts": 0,
  "last_fetch_attempt": "2017-12-04T21:39:13.447537Z",
  "failure": null,
  "can_resubmit": false,
  "resubmitted_count": 0,
  "job_id": "70845",
  "job_status": "Complete",
  "backend": "https://qa-reports.linaro.org/api/backends/2/",
  "testrun": "https://qa-reports.linaro.org/api/testruns/154629/",
  "target": "https://qa-reports.linaro.org/api/projects/40/",
  "target_build": "https://qa-reports.linaro.org/api/builds/3311/",
  "parent_job": null
}