{
  "url": "https://qa-reports.linaro.org/api/testjobs/190364/",
  "external_url": "https://lkft.validation.linaro.org/scheduler/job/101998",
  "definition": "https://qa-reports.linaro.org/api/testjobs/190364/definition/",
  "name": "lkft-ltp-sched-linux-4.9.y-170",
  "environment": "x86",
  "created_at": "2018-01-24T13:24:28.349212Z",
  "submitted_at": "2018-01-24T13:24:28.859666Z",
  "fetched_at": "2018-01-24T14:17:36.729539Z",
  "submitted": true,
  "fetched": true,
  "fetch_attempts": 0,
  "last_fetch_attempt": "2018-01-24T14:17:36.057763Z",
  "failure": null,
  "can_resubmit": false,
  "resubmitted_count": 0,
  "job_id": "101998",
  "job_status": "Complete",
  "backend": "https://qa-reports.linaro.org/api/backends/2/",
  "testrun": "https://qa-reports.linaro.org/api/testruns/190802/",
  "target": "https://qa-reports.linaro.org/api/projects/23/",
  "target_build": "https://qa-reports.linaro.org/api/builds/4037/",
  "parent_job": null
}