{
  "url": "https://qa-reports.linaro.org/api/testjobs/195044/",
  "external_url": "https://lkft.validation.linaro.org/scheduler/job/106981",
  "definition": "https://qa-reports.linaro.org/api/testjobs/195044/definition/",
  "name": "lkft-ltp-cap_bounds-linux-4.4.y-128",
  "environment": "x86",
  "created_at": "2018-01-31T15:03:27.328282Z",
  "submitted_at": "2018-01-31T15:03:27.845148Z",
  "fetched_at": "2018-01-31T15:18:08.436067Z",
  "submitted": true,
  "fetched": true,
  "fetch_attempts": 0,
  "last_fetch_attempt": "2018-01-31T15:18:06.430674Z",
  "failure": null,
  "can_resubmit": false,
  "resubmitted_count": 0,
  "job_id": "106981",
  "job_status": "Complete",
  "backend": "https://qa-reports.linaro.org/api/backends/2/",
  "testrun": "https://qa-reports.linaro.org/api/testruns/195334/",
  "target": "https://qa-reports.linaro.org/api/projects/40/",
  "target_build": "https://qa-reports.linaro.org/api/builds/4164/",
  "parent_job": null
}