{
  "url": "https://qa-reports.linaro.org/api/testjobs/222131/",
  "external_url": "https://lkft.validation.linaro.org/scheduler/job/119322",
  "definition": "https://qa-reports.linaro.org/api/testjobs/222131/definition/",
  "name": "lkft-kselftests-linux-4.9.y-186",
  "environment": "juno-r2",
  "created_at": "2018-02-15T15:29:21.188945Z",
  "submitted_at": "2018-02-15T15:29:21.751679Z",
  "fetched_at": "2018-02-15T16:18:15.064530Z",
  "submitted": true,
  "fetched": true,
  "fetch_attempts": 0,
  "last_fetch_attempt": "2018-02-15T16:18:12.614163Z",
  "failure": null,
  "can_resubmit": false,
  "resubmitted_count": 0,
  "job_id": "119322",
  "job_status": "Complete",
  "backend": "https://qa-reports.linaro.org/api/backends/2/",
  "testrun": "https://qa-reports.linaro.org/api/testruns/222727/",
  "target": "https://qa-reports.linaro.org/api/projects/23/",
  "target_build": "https://qa-reports.linaro.org/api/builds/4452/",
  "parent_job": null
}