{
  "url": "https://qa-reports.linaro.org/api/testjobs/222159/",
  "external_url": "https://lkft.validation.linaro.org/scheduler/job/119346",
  "definition": "https://qa-reports.linaro.org/api/testjobs/222159/definition/",
  "name": "lkft-ltp-fcntl-locktests-linux-4.9.y-186",
  "environment": "x15",
  "created_at": "2018-02-15T15:39:10.572408Z",
  "submitted_at": "2018-02-15T15:39:11.133349Z",
  "fetched_at": "2018-02-15T16:17:36.561969Z",
  "submitted": true,
  "fetched": true,
  "fetch_attempts": 0,
  "last_fetch_attempt": "2018-02-15T16:17:34.324123Z",
  "failure": null,
  "can_resubmit": false,
  "resubmitted_count": 0,
  "job_id": "119346",
  "job_status": "Complete",
  "backend": "https://qa-reports.linaro.org/api/backends/2/",
  "testrun": "https://qa-reports.linaro.org/api/testruns/222711/",
  "target": "https://qa-reports.linaro.org/api/projects/23/",
  "target_build": "https://qa-reports.linaro.org/api/builds/4452/",
  "parent_job": null
}