{
  "url": "https://qa-reports.linaro.org/api/testjobs/263978/",
  "external_url": "https://lkft.validation.linaro.org/scheduler/job/148301",
  "definition": "https://qa-reports.linaro.org/api/testjobs/263978/definition/",
  "name": "lkft-ltp-fsx-linux-4.9.y-208",
  "environment": "juno-r2",
  "created_at": "2018-03-16T17:39:03.260487Z",
  "submitted_at": "2018-03-16T17:39:03.795233Z",
  "fetched_at": "2018-03-16T18:16:02.640442Z",
  "submitted": true,
  "fetched": true,
  "fetch_attempts": 0,
  "last_fetch_attempt": "2018-03-16T18:16:00.708947Z",
  "failure": null,
  "can_resubmit": false,
  "resubmitted_count": 0,
  "job_id": "148301",
  "job_status": "Complete",
  "backend": "https://qa-reports.linaro.org/api/backends/2/",
  "testrun": "https://qa-reports.linaro.org/api/testruns/253706/",
  "target": "https://qa-reports.linaro.org/api/projects/23/",
  "target_build": "https://qa-reports.linaro.org/api/builds/5053/",
  "parent_job": null
}