{
  "url": "https://qa-reports.linaro.org/api/testjobs/275558/",
  "external_url": "https://lkft.validation.linaro.org/scheduler/job/160514",
  "definition": "https://qa-reports.linaro.org/api/testjobs/275558/definition/",
  "name": "lkft-ltp-math-linux-4.9.y-219",
  "environment": "juno-r2",
  "created_at": "2018-03-27T19:53:13.576860Z",
  "submitted_at": "2018-03-27T19:53:14.130030Z",
  "fetched_at": "2018-03-27T21:00:00.316756Z",
  "submitted": true,
  "fetched": true,
  "fetch_attempts": 0,
  "last_fetch_attempt": "2018-03-27T20:59:58.215902Z",
  "failure": null,
  "can_resubmit": false,
  "resubmitted_count": 0,
  "job_id": "160514",
  "job_status": "Complete",
  "backend": "https://qa-reports.linaro.org/api/backends/2/",
  "testrun": "https://qa-reports.linaro.org/api/testruns/265117/",
  "target": "https://qa-reports.linaro.org/api/projects/23/",
  "target_build": "https://qa-reports.linaro.org/api/builds/5235/",
  "parent_job": null
}