{
  "url": "https://qa-reports.linaro.org/api/testjobs/635312/",
  "external_url": "https://lkft.validation.linaro.org/scheduler/job/220148",
  "definition": "https://qa-reports.linaro.org/api/testjobs/635312/definition/",
  "name": "lkft-ltp-pty-linux-4.9.y-261",
  "environment": "hi6220-hikey",
  "created_at": "2018-05-18T08:51:07.514996Z",
  "submitted_at": "2018-05-18T08:51:08.086856Z",
  "fetched_at": "2018-05-18T09:29:33.276383Z",
  "submitted": true,
  "fetched": true,
  "fetch_attempts": 0,
  "last_fetch_attempt": "2018-05-18T09:29:31.263602Z",
  "failure": null,
  "can_resubmit": false,
  "resubmitted_count": 0,
  "job_id": "220148",
  "job_status": "Complete",
  "backend": "https://qa-reports.linaro.org/api/backends/2/",
  "testrun": "https://qa-reports.linaro.org/api/testruns/440286/",
  "target": "https://qa-reports.linaro.org/api/projects/23/",
  "target_build": "https://qa-reports.linaro.org/api/builds/6651/",
  "parent_job": null
}