{
  "url": "https://qa-reports.linaro.org/api/testjobs/828770/",
  "external_url": "https://lkft.validation.linaro.org/scheduler/job/280143",
  "definition": "https://qa-reports.linaro.org/api/testjobs/828770/definition/",
  "name": "lkft-ltp-math-linux-4.9.y-294",
  "environment": "qemu_x86_64",
  "created_at": "2018-06-14T15:12:42.626956Z",
  "submitted_at": "2018-06-14T15:12:43.179788Z",
  "fetched_at": "2018-06-14T16:41:04.109678Z",
  "submitted": true,
  "fetched": true,
  "fetch_attempts": 0,
  "last_fetch_attempt": "2018-06-14T16:41:02.263102Z",
  "failure": null,
  "can_resubmit": false,
  "resubmitted_count": 0,
  "job_id": "280143",
  "job_status": "Complete",
  "backend": "https://qa-reports.linaro.org/api/backends/2/",
  "testrun": "https://qa-reports.linaro.org/api/testruns/592983/",
  "target": "https://qa-reports.linaro.org/api/projects/23/",
  "target_build": "https://qa-reports.linaro.org/api/builds/7528/",
  "parent_job": null
}