{
  "url": "https://qa-reports.linaro.org/api/testjobs/864737/",
  "external_url": "https://lkft.validation.linaro.org/scheduler/job/294133",
  "definition": "https://qa-reports.linaro.org/api/testjobs/864737/definition/",
  "name": "lkft-ltp-cve-linux-4.4.y-237",
  "environment": "qemu_x86_64",
  "created_at": "2018-06-20T21:43:32.514720Z",
  "submitted_at": "2018-06-20T21:43:33.065800Z",
  "fetched_at": "2018-06-20T22:24:48.412608Z",
  "submitted": true,
  "fetched": true,
  "fetch_attempts": 0,
  "last_fetch_attempt": "2018-06-20T22:24:46.140254Z",
  "failure": null,
  "can_resubmit": false,
  "resubmitted_count": 0,
  "job_id": "294133",
  "job_status": "Complete",
  "backend": "https://qa-reports.linaro.org/api/backends/2/",
  "testrun": "https://qa-reports.linaro.org/api/testruns/618202/",
  "target": "https://qa-reports.linaro.org/api/projects/40/",
  "target_build": "https://qa-reports.linaro.org/api/builds/7615/",
  "parent_job": null
}