{
  "url": "https://qa-reports.linaro.org/api/testjobs/882941/",
  "external_url": "https://lkft.validation.linaro.org/scheduler/job/318917",
  "definition": "https://qa-reports.linaro.org/api/testjobs/882941/definition/",
  "name": "lkft-kselftests-linux-4.4.y-244",
  "environment": "x86",
  "created_at": "2018-07-08T14:09:30.705986Z",
  "submitted_at": "2018-07-08T14:09:31.261864Z",
  "fetched_at": "2018-07-08T14:28:58.484388Z",
  "submitted": true,
  "fetched": true,
  "fetch_attempts": 0,
  "last_fetch_attempt": "2018-07-08T14:28:55.540383Z",
  "failure": null,
  "can_resubmit": false,
  "resubmitted_count": 0,
  "job_id": "318917",
  "job_status": "Complete",
  "backend": "https://qa-reports.linaro.org/api/backends/2/",
  "testrun": "https://qa-reports.linaro.org/api/testruns/691333/",
  "target": "https://qa-reports.linaro.org/api/projects/40/",
  "target_build": "https://qa-reports.linaro.org/api/builds/7966/",
  "parent_job": null
}