{
  "url": "https://qa-reports.linaro.org/api/testjobs/921134/",
  "external_url": "https://lkft.validation.linaro.org/scheduler/job/330557",
  "definition": "https://qa-reports.linaro.org/api/testjobs/921134/definition/",
  "name": "lkft-ltp-math-linux-4.4.y-251",
  "environment": "x15",
  "created_at": "2018-07-17T11:55:41.265338Z",
  "submitted_at": "2018-07-17T11:55:41.807053Z",
  "fetched_at": "2018-07-17T13:44:47.239463Z",
  "submitted": true,
  "fetched": true,
  "fetch_attempts": 0,
  "last_fetch_attempt": "2018-07-17T13:44:45.179692Z",
  "failure": null,
  "can_resubmit": false,
  "resubmitted_count": 0,
  "job_id": "330557",
  "job_status": "Complete",
  "backend": "https://qa-reports.linaro.org/api/backends/2/",
  "testrun": "https://qa-reports.linaro.org/api/testruns/725215/",
  "target": "https://qa-reports.linaro.org/api/projects/40/",
  "target_build": "https://qa-reports.linaro.org/api/builds/8155/",
  "parent_job": null
}