{
  "kselftest__version": "4.14",
  "ltp-math-tests__url": "git://github.com/linux-test-project/ltp.git",
  "ltp-pty-tests__url": "git://github.com/linux-test-project/ltp.git",
  "ltp-fs_bind-tests__revision": "e671f2a13c695bbd87f7dfec2954ca7e3c43f377",
  "ltp-fs_bind-tests__version": "20170929",
  "job_status": "Complete",
  "ltp-timers-tests__revision": "e671f2a13c695bbd87f7dfec2954ca7e3c43f377",
  "kernel-defconfig": [
    "http://snapshots.linaro.org/openembedded/lkft/morty/am57xx-evm/rpb/linux-stable-rc-4.9/128/defconfig",
    "http://snapshots.linaro.org/openembedded/lkft/morty/hikey/rpb/linux-stable-rc-4.9/128/defconfig",
    "http://snapshots.linaro.org/openembedded/lkft/morty/intel-core2-32/rpb/linux-stable-rc-4.9/128/defconfig",
    "http://snapshots.linaro.org/openembedded/lkft/morty/juno/rpb/linux-stable-rc-4.9/128/defconfig"
  ],
  "build-location": [
    "http://snapshots.linaro.org/openembedded/lkft/morty/am57xx-evm/rpb/linux-stable-rc-4.9/128",
    "http://snapshots.linaro.org/openembedded/lkft/morty/hikey/rpb/linux-stable-rc-4.9/128",
    "http://snapshots.linaro.org/openembedded/lkft/morty/intel-core2-32/rpb/linux-stable-rc-4.9/128",
    "http://snapshots.linaro.org/openembedded/lkft/morty/juno/rpb/linux-stable-rc-4.9/128"
  ],
  "ltp-fs_perms_simple-tests__revision": "e671f2a13c695bbd87f7dfec2954ca7e3c43f377",
  "ltp-ipc-tests__revision": "e671f2a13c695bbd87f7dfec2954ca7e3c43f377",
  "ltp-securebits-tests__revision": "e671f2a13c695bbd87f7dfec2954ca7e3c43f377",
  "ltp-ipc-tests__url": "git://github.com/linux-test-project/ltp.git",
  "git describe": "v4.9.71-105-g73a512247458",
  "kselftest__revision": "4.14",
  "ltp-filecaps-tests__revision": "e671f2a13c695bbd87f7dfec2954ca7e3c43f377",
  "ltp-fs_bind-tests__url": "git://github.com/linux-test-project/ltp.git",
  "ltp-timers-tests__version": "20170929",
  "ltp-ipc-tests__version": "20170929",
  "ltp-syscalls-tests__url": "git://github.com/linux-test-project/ltp.git",
  "libhugetlbfs__version": "2.20+gitAUTOINC+02df38e93e+next",
  "ltp-fs-tests__version": "20170929",
  "ltp-containers-tests__version": "20170929",
  "ltp-securebits-tests__url": "git://github.com/linux-test-project/ltp.git",
  "ltp-nptl-tests__url": "git://github.com/linux-test-project/ltp.git",
  "ltp-io-tests__url": "git://github.com/linux-test-project/ltp.git",
  "series": "lkft",
  "ltp-math-tests__revision": "e671f2a13c695bbd87f7dfec2954ca7e3c43f377",
  "ltp-filecaps-tests__version": "20170929",
  "ltp-fcntl-locktests-tests__url": "git://github.com/linux-test-project/ltp.git",
  "ltp-fs_perms_simple-tests__version": "20170929",
  "ltp-hugetlb-tests__revision": "e671f2a13c695bbd87f7dfec2954ca7e3c43f377",
  "ltp-pty-tests__version": "20170929",
  "ltp-fsx-tests__version": "20170929",
  "ltp-math-tests__version": "20170929",
  "ltp-hugetlb-tests__version": "20170929",
  "ltp-containers-tests__url": "git://github.com/linux-test-project/ltp.git",
  "ltp-cap_bounds-tests__url": "git://github.com/linux-test-project/ltp.git",
  "ltp-sched-tests__url": "git://github.com/linux-test-project/ltp.git",
  "ltp-io-tests__version": "20170929",
  "ltp-io-tests__revision": "e671f2a13c695bbd87f7dfec2954ca7e3c43f377",
  "ltp-nptl-tests__version": "20170929",
  "ltp-fs_perms_simple-tests__url": "git://github.com/linux-test-project/ltp.git",
  "ltp-fsx-tests__revision": "e671f2a13c695bbd87f7dfec2954ca7e3c43f377",
  "make_kernelversion": "4.9.72-rc1",
  "ltp-cap_bounds-tests__version": "20170929",
  "git commit": "73a512247458248b7ceea536cfa812adb5bdd680",
  "ltp-cap_bounds-tests__revision": "e671f2a13c695bbd87f7dfec2954ca7e3c43f377",
  "ltp-fsx-tests__url": "git://github.com/linux-test-project/ltp.git",
  "ltp-securebits-tests__version": "20170929",
  "job_id": [
    "82731",
    "82732",
    "82733",
    "82734",
    "82735",
    "82736",
    "82737",
    "82738",
    "82739",
    "82740",
    "82741",
    "82742",
    "82743",
    "82744",
    "82745",
    "82746",
    "82747",
    "82748",
    "82749",
    "82750",
    "82751",
    "82752",
    "82753",
    "82754",
    "82755",
    "82756",
    "82757",
    "82758",
    "82759",
    "82760",
    "82761",
    "82762",
    "82763",
    "82764",
    "82765",
    "82766",
    "82767",
    "82768",
    "82769",
    "82770",
    "82771",
    "82772",
    "82773",
    "82774",
    "82775",
    "82776",
    "82777",
    "82778",
    "82779",
    "82780",
    "82781",
    "82782",
    "82783",
    "82784",
    "82785",
    "82786",
    "82787",
    "82788",
    "82789",
    "82790",
    "82791",
    "82792",
    "82793",
    "82794",
    "82795",
    "82796",
    "82797",
    "82798",
    "82799",
    "82800",
    "82801",
    "82802",
    "82803",
    "82804",
    "82805",
    "82806",
    "82807",
    "82808",
    "82809",
    "82810"
  ],
  "ltp-syscalls-tests__version": "20170929",
  "ltp-syscalls-tests__revision": "e671f2a13c695bbd87f7dfec2954ca7e3c43f377",
  "build-url": [
    "https://ci.linaro.org/job/openembedded-lkft-linux-stable-rc-4.9/DISTRO=rpb,MACHINE=am57xx-evm,label=docker-lkft/128/",
    "https://ci.linaro.org/job/openembedded-lkft-linux-stable-rc-4.9/DISTRO=rpb,MACHINE=hikey,label=docker-lkft/128/",
    "https://ci.linaro.org/job/openembedded-lkft-linux-stable-rc-4.9/DISTRO=rpb,MACHINE=intel-core2-32,label=docker-lkft/128/",
    "https://ci.linaro.org/job/openembedded-lkft-linux-stable-rc-4.9/DISTRO=rpb,MACHINE=juno,label=docker-lkft/128/"
  ],
  "git branch": "linux-4.9.y",
  "ltp-timers-tests__url": "git://github.com/linux-test-project/ltp.git",
  "ltp-fcntl-locktests-tests__version": "20170929",
  "ltp-pty-tests__revision": "e671f2a13c695bbd87f7dfec2954ca7e3c43f377",
  "job_url": [
    "https://lkft.validation.linaro.org/scheduler/job/82731",
    "https://lkft.validation.linaro.org/scheduler/job/82732",
    "https://lkft.validation.linaro.org/scheduler/job/82733",
    "https://lkft.validation.linaro.org/scheduler/job/82734",
    "https://lkft.validation.linaro.org/scheduler/job/82735",
    "https://lkft.validation.linaro.org/scheduler/job/82736",
    "https://lkft.validation.linaro.org/scheduler/job/82737",
    "https://lkft.validation.linaro.org/scheduler/job/82738",
    "https://lkft.validation.linaro.org/scheduler/job/82739",
    "https://lkft.validation.linaro.org/scheduler/job/82740",
    "https://lkft.validation.linaro.org/scheduler/job/82741",
    "https://lkft.validation.linaro.org/scheduler/job/82742",
    "https://lkft.validation.linaro.org/scheduler/job/82743",
    "https://lkft.validation.linaro.org/scheduler/job/82744",
    "https://lkft.validation.linaro.org/scheduler/job/82745",
    "https://lkft.validation.linaro.org/scheduler/job/82746",
    "https://lkft.validation.linaro.org/scheduler/job/82747",
    "https://lkft.validation.linaro.org/scheduler/job/82748",
    "https://lkft.validation.linaro.org/scheduler/job/82749",
    "https://lkft.validation.linaro.org/scheduler/job/82750",
    "https://lkft.validation.linaro.org/scheduler/job/82751",
    "https://lkft.validation.linaro.org/scheduler/job/82752",
    "https://lkft.validation.linaro.org/scheduler/job/82753",
    "https://lkft.validation.linaro.org/scheduler/job/82754",
    "https://lkft.validation.linaro.org/scheduler/job/82755",
    "https://lkft.validation.linaro.org/scheduler/job/82756",
    "https://lkft.validation.linaro.org/scheduler/job/82757",
    "https://lkft.validation.linaro.org/scheduler/job/82758",
    "https://lkft.validation.linaro.org/scheduler/job/82759",
    "https://lkft.validation.linaro.org/scheduler/job/82760",
    "https://lkft.validation.linaro.org/scheduler/job/82761",
    "https://lkft.validation.linaro.org/scheduler/job/82762",
    "https://lkft.validation.linaro.org/scheduler/job/82763",
    "https://lkft.validation.linaro.org/scheduler/job/82764",
    "https://lkft.validation.linaro.org/scheduler/job/82765",
    "https://lkft.validation.linaro.org/scheduler/job/82766",
    "https://lkft.validation.linaro.org/scheduler/job/82767",
    "https://lkft.validation.linaro.org/scheduler/job/82768",
    "https://lkft.validation.linaro.org/scheduler/job/82769",
    "https://lkft.validation.linaro.org/scheduler/job/82770",
    "https://lkft.validation.linaro.org/scheduler/job/82771",
    "https://lkft.validation.linaro.org/scheduler/job/82772",
    "https://lkft.validation.linaro.org/scheduler/job/82773",
    "https://lkft.validation.linaro.org/scheduler/job/82774",
    "https://lkft.validation.linaro.org/scheduler/job/82775",
    "https://lkft.validation.linaro.org/scheduler/job/82776",
    "https://lkft.validation.linaro.org/scheduler/job/82777",
    "https://lkft.validation.linaro.org/scheduler/job/82778",
    "https://lkft.validation.linaro.org/scheduler/job/82779",
    "https://lkft.validation.linaro.org/scheduler/job/82780",
    "https://lkft.validation.linaro.org/scheduler/job/82781",
    "https://lkft.validation.linaro.org/scheduler/job/82782",
    "https://lkft.validation.linaro.org/scheduler/job/82783",
    "https://lkft.validation.linaro.org/scheduler/job/82784",
    "https://lkft.validation.linaro.org/scheduler/job/82785",
    "https://lkft.validation.linaro.org/scheduler/job/82786",
    "https://lkft.validation.linaro.org/scheduler/job/82787",
    "https://lkft.validation.linaro.org/scheduler/job/82788",
    "https://lkft.validation.linaro.org/scheduler/job/82789",
    "https://lkft.validation.linaro.org/scheduler/job/82790",
    "https://lkft.validation.linaro.org/scheduler/job/82791",
    "https://lkft.validation.linaro.org/scheduler/job/82792",
    "https://lkft.validation.linaro.org/scheduler/job/82793",
    "https://lkft.validation.linaro.org/scheduler/job/82794",
    "https://lkft.validation.linaro.org/scheduler/job/82795",
    "https://lkft.validation.linaro.org/scheduler/job/82796",
    "https://lkft.validation.linaro.org/scheduler/job/82797",
    "https://lkft.validation.linaro.org/scheduler/job/82798",
    "https://lkft.validation.linaro.org/scheduler/job/82799",
    "https://lkft.validation.linaro.org/scheduler/job/82800",
    "https://lkft.validation.linaro.org/scheduler/job/82801",
    "https://lkft.validation.linaro.org/scheduler/job/82802",
    "https://lkft.validation.linaro.org/scheduler/job/82803",
    "https://lkft.validation.linaro.org/scheduler/job/82804",
    "https://lkft.validation.linaro.org/scheduler/job/82805",
    "https://lkft.validation.linaro.org/scheduler/job/82806",
    "https://lkft.validation.linaro.org/scheduler/job/82807",
    "https://lkft.validation.linaro.org/scheduler/job/82808",
    "https://lkft.validation.linaro.org/scheduler/job/82809",
    "https://lkft.validation.linaro.org/scheduler/job/82810"
  ],
  "kselftest__url": "https://www.kernel.org/pub/linux/kernel/v4.x/linux-4.14.tar.xz",
  "kernel-config": [
    "http://snapshots.linaro.org/openembedded/lkft/morty/am57xx-evm/rpb/linux-stable-rc-4.9/128/config",
    "http://snapshots.linaro.org/openembedded/lkft/morty/hikey/rpb/linux-stable-rc-4.9/128/config",
    "http://snapshots.linaro.org/openembedded/lkft/morty/intel-core2-32/rpb/linux-stable-rc-4.9/128/config",
    "http://snapshots.linaro.org/openembedded/lkft/morty/juno/rpb/linux-stable-rc-4.9/128/config"
  ],
  "libhugetlbfs__revision": "02df38e93e25e07f4d54edae94fb4ec90b7a2824",
  "ltp-fs-tests__revision": "e671f2a13c695bbd87f7dfec2954ca7e3c43f377",
  "git repo": "https://git.kernel.org/pub/scm/linux/kernel/git/stable/linux-stable-rc.git",
  "ltp-fcntl-locktests-tests__revision": "e671f2a13c695bbd87f7dfec2954ca7e3c43f377",
  "ltp-filecaps-tests__url": "git://github.com/linux-test-project/ltp.git",
  "ltp-containers-tests__revision": "e671f2a13c695bbd87f7dfec2954ca7e3c43f377",
  "ltp-nptl-tests__revision": "e671f2a13c695bbd87f7dfec2954ca7e3c43f377",
  "ltp-hugetlb-tests__url": "git://github.com/linux-test-project/ltp.git",
  "ltp-sched-tests__revision": "e671f2a13c695bbd87f7dfec2954ca7e3c43f377",
  "libhugetlbfs__url": "git://github.com/libhugetlbfs/libhugetlbfs.git",
  "ltp-sched-tests__version": "20170929",
  "ltp-fs-tests__url": "git://github.com/linux-test-project/ltp.git"
}